slippire.py
slippire-0.0.1.dist-info/LICENSE
slippire-0.0.1.dist-info/WHEEL
slippire-0.0.1.dist-info/METADATA
slippire-0.0.1.dist-info/RECORD
