Metadata-Version: 2.1
Name: slippire
Version: 0.0.1
Summary: slippire
Author-email: charlie gruhler <chgruhler@gmail.com>
Classifier: License :: OSI Approved :: MIT License
